pyawscron/__init__.py
pyawscron/awscron.py
pyawscron/commons.py
pyawscron/occurrence.py
pyawscron/version.py
pyawscron-1.0.7.dist-info/LICENSE
pyawscron-1.0.7.dist-info/METADATA
pyawscron-1.0.7.dist-info/WHEEL
pyawscron-1.0.7.dist-info/top_level.txt
pyawscron-1.0.7.dist-info/RECORD
