Metadata-Version: 2.1
Name: pyawscron
Version: 1.0.7
Summary: An AWS Cron Parser
Home-page: https://github.com/pitchblack408/pyawscron
Author: Michael Martin
Author-email: pitchblack408@gmail.com
Project-URL: Bug Tracker, https://github.com/pitchblack408/pyawscron/issues
Classifier: Programming Language :: Python :: 3
Classifier: License :: OSI Approved :: BSD License
Classifier: Operating System :: OS Independent
Requires-Python: >=3.6
License-File: LICENSE
Requires-Dist: python-dateutil>=2.8.1
